<?xml version="1.0" encoding="utf-8" ?>
<dwsync>
<file name="indesign-training-intro.html" server="cdt-test010.worldsecuresystems.com//" local="130595576943534308" remote="130596016540000000" Dst="0" />
<file name="indesign-training-advanced.html" server="cdt-test010.worldsecuresystems.com//" local="130595576943514331" remote="130596016550000000" Dst="0" />
<file name="advanced-indesign-long-documents.html" server="cdt-test010.worldsecuresystems.com//" local="130595576943284233" remote="130596016620000000" Dst="0" />
<file name="indesign-interactivity-training.html" server="cdt-test010.worldsecuresystems.com//" local="130595576943434243" remote="130596016560000000" Dst="0" />
<file name="indesign-accessibility-training.html" server="cdt-test010.worldsecuresystems.com//" local="130595576943414329" remote="130596016580000000" Dst="0" />
<file name="photoshop-training-intro.html" server="cdt-test010.worldsecuresystems.com//" local="130595576943604272" remote="130596016510000000" Dst="0" />
<file name="photoshop-training-advanced.html" server="cdt-test010.worldsecuresystems.com//" local="130595576943564269" remote="130596016530000000" Dst="0" />
<file name="photoshop-web-training.html" server="cdt-test010.worldsecuresystems.com//" local="130595576943624285" remote="130596016500000000" Dst="0" />
<file name="illustrator-training-intro.html" server="cdt-test010.worldsecuresystems.com//" local="130595576943394264" remote="130596016590000000" Dst="0" />
<file name="illustrator-training-advanced.html" server="cdt-test010.worldsecuresystems.com//" local="130595576943364291" remote="130596016600000000" Dst="0" />
<file name="acrobat-essentials.html" server="cdt-test010.worldsecuresystems.com//" local="130595576943194250" remote="130596016650000000" Dst="0" />
<file name="acrobat-forms.html" server="cdt-test010.worldsecuresystems.com//" local="130595576943214210" remote="130596016630000000" Dst="0" />
<file name="indesign-to-epubs-training.html" server="cdt-test010.worldsecuresystems.com//" local="130595584294465633" remote="130596016440000000" Dst="0" />
<file name="adobe-dps-single-edition-training.html" server="cdt-test010.worldsecuresystems.com//" local="130596050045284591" remote="130596016420000000" Dst="0" />
<file name="adobe-dps-professional-training.html" server="cdt-test010.worldsecuresystems.com//" local="130595584294365632" remote="130596016460000000" Dst="0" />
<file name="digital-magazine-mobile-devices-training.html" server="cdt-test010.worldsecuresystems.com//" local="130596050140157419" remote="130596016370000000" Dst="0" />
<file name="flash-actionscript-training-intro.html" server="cdt-test010.worldsecuresystems.com//" local="130595577229418555" remote="130596016480000000" Dst="0" />
<file name="flash-training-intro.html" server="cdt-test010.worldsecuresystems.com//" local="130595577229438234" remote="130596016470000000" Dst="0" />
<file name="css-training.html" server="cdt-test010.worldsecuresystems.com//" local="130596047304846196" remote="130596016430000000" Dst="0" />
<file name="html-training-intro.html" server="cdt-test010.worldsecuresystems.com//" local="130596050326700826" remote="130596016310000000" Dst="0" />
<file name="dreamweaver-training-intro.html" server="cdt-test010.worldsecuresystems.com//" local="130596050215196683" remote="130596016320000000" Dst="0" />
<file name="X.html" server="cdt-test010.worldsecuresystems.com//" local="130596050563166314" remote="130596015820000000" Dst="0" />
</dwsync>