<?xml version="1.0" encoding="utf-8" ?><dwsync><file name="html5.js" server="cdt-test010.worldsecuresystems.com//" local="3492487903" remote="-4611800415683796257" Dst="-1" /><file name="jquery.nivo.slider.pack.js" server="cdt-test010.worldsecuresystems.com//" local="3492487903" remote="-4611800415683796257" Dst="-1" /><file name="jquery.validate.js" server="cdt-test010.worldsecuresystems.com//" local="3492487903" remote="-4611800415683796257" Dst="-1" /><file name="menu.js" server="cdt-test010.worldsecuresystems.com//" local="3492487903" remote="-4611800415683796257" Dst="-1" /><file name="mobile.js" server="cdt-test010.worldsecuresystems.com//" local="3492487903" remote="-4611800415683796257" Dst="-1" /><file name="html5.js" server="cdt-test02.worldsecuresystems.com//" local="3498428568" remote="-4611800415677849169" Dst="-1" /><file name="jquery.nivo.slider.pack.js" server="cdt-test02.worldsecuresystems.com//" local="3498428568" remote="-4611800415677849169" Dst="-1" /><file name="jquery.validate.js" server="cdt-test02.worldsecuresystems.com//" local="3498428568" remote="-4611800415677602584" Dst="-1" /><file name="menu.js" server="cdt-test02.worldsecuresystems.com//" local="3498428568" remote="-4611800415677602584" Dst="-1" /><file name="mobile.js" server="cdt-test02.worldsecuresystems.com//" local="3498428568" remote="-4611800415677849168" Dst="-1" /></dwsync>